wattpad_scraper/__init__.py
wattpad_scraper/wattpad_downloader.py
wattpad_scraper/models/__init__.py
wattpad_scraper/test/__init__.py
wattpad_scraper/test/test_download.py
wattpad_scraper/test/test_wattpad_downloader.py
wattpad_scraper/utils/__init__.py
wattpad_scraper/utils/convert_to_epub.py
wattpad_scraper/utils/log.py
wattpad_scraper/utils/parse_content.py
wattpad_scraper/utils/request.py
jb_wattpad_scraper-0.0.40.dist-info/LICENSE
jb_wattpad_scraper-0.0.40.dist-info/METADATA
jb_wattpad_scraper-0.0.40.dist-info/WHEEL
jb_wattpad_scraper-0.0.40.dist-info/top_level.txt
jb_wattpad_scraper-0.0.40.dist-info/RECORD
