Metadata-Version: 2.1
Name: jb-wattpad-scraper
Version: 0.0.40
Summary: Get wattpad stories and chapters, and download them as ebook
Home-page: https://github.com/josyelbuenos/jb-wattpad-scraper
Author: Josyel Buenos
Author-email: josyelbuenos@gmail.com
License: MIT
Classifier: Development Status :: 4 - Beta
Classifier: Intended Audience :: Developers
Classifier: License :: OSI Approved :: MIT License
Classifier: Operating System :: OS Independent
Classifier: Programming Language :: Python :: 3
Classifier: Programming Language :: Python :: 3.6
Classifier: Programming Language :: Python :: 3.7
Classifier: Programming Language :: Python :: 3.8
License-File: LICENSE
Requires-Dist: bs4==0.0.1
Requires-Dist: EbookLib==0.17.1
Requires-Dist: fake-headers==1.0.2
Requires-Dist: httpx==0.23.3
